{
  "1": [
    "\"n02119789\"",
    "[\"kit fox\", \"Vulpes macrotis\"],"
  ],
  "2": [
    "\"n02100735\"",
    "[\"English setter\"],"
  ],
  "3": [
    "n02096294",
    "Australian terrier"
  ],
  "4": [
    "n02066245",
    "grey whale, gray whale, devilfish, Eschrichtius gibbosus, Eschrichtius robustus"
  ],
  "5": [
    "n02509815",
    "lesser panda, red panda, panda, bear cat, cat bear, Ailurus fulgens"
  ],
  "6": [
    "n02124075",
    "Egyptian cat"
  ],
  "7": [
    "n02417914",
    "ibex, Capra ibex"
  ],
  "8": [
    "n02123394",
    "Persian cat"
  ],
  "9": [
    "n02125311",
    "cougar, puma, catamount, mountain lion, painter, panther, Felis concolor"
  ],
  "10": [
    "n02423022",
    "gazelle"
  ],
  "11": [
    "n02346627",
    "porcupine, hedgehog"
  ],
  "12": [
    "n02077923",
    "sea lion"
  ],
  "13": [
    "n02447366",
    "badger"
  ],
  "14": [
    "n02109047",
    "Great Dane"
  ],
  "15": [
    "n02092002",
    "Scottish deerhound, deerhound"
  ],
  "16": [
    "n02071294",
    "killer whale, killer, orca, grampus, sea wolf, Orcinus orca"
  ],
  "17": [
    "n02442845",
    "mink"
  ],
  "18": [
    "n02504458",
    "African elephant, Loxodonta africana"
  ],
  "19": [
    "n02114712",
    "red wolf, maned wolf, Canis rufus, Canis niger"
  ],
  "20": [
    "n02128925",
    "jaguar, panther, Panthera onca, Felis onca"
  ],
  "21": [
    "n02117135",
    "hyena, hyaena"
  ],
  "22": [
    "n02493509",
    "titi, titi monkey"
  ],
  "23": [
    "n02457408",
    "three-toed sloth, ai, Bradypus tridactylus"
  ],
  "24": [
    "n02389026",
    "sorrel"
  ],
  "25": [
    "n02443484",
    "black-footed ferret, ferret, Mustela nigripes"
  ],
  "26": [
    "n02110341",
    "dalmatian, coach dog, carriage dog"
  ],
  "27": [
    "n02093256",
    "Staffordshire bullterrier, Staffordshire bull terrier"
  ],
  "28": [
    "n02106382",
    "Bouvier des Flandres, Bouviers des Flandres"
  ],
  "29": [
    "n02441942",
    "weasel"
  ],
  "30": [
    "n02113712",
    "miniature poodle"
  ],
  "31": [
    "n02415577",
    "bighorn, bighorn sheep, cimarron, Rocky Mountain bighorn, Rocky Mountain sheep, Ovis canadensis"
  ],
  "32": [
    "n02356798",
    "fox squirrel, eastern fox squirrel, Sciurus niger"
  ],
  "33": [
    "n02488702",
    "colobus, colobus monkey"
  ],
  "34": [
    "n02123159",
    "tiger cat"
  ],
  "35": [
    "n02422699",
    "impala, Aepyceros melampus"
  ],
  "36": [
    "n02114855",
    "coyote, prairie wolf, brush wolf, Canis latrans"
  ],
  "37": [
    "n02094433",
    "Yorkshire terrier"
  ],
  "38": [
    "n02111277",
    "Newfoundland, Newfoundland dog"
  ],
  "39": [
    "n02119022",
    "red fox, Vulpes vulpes"
  ],
  "40": [
    "n02422106",
    "hartebeest"
  ],
  "41": [
    "n02120505",
    "grey fox, gray fox, Urocyon cinereoargenteus"
  ],
  "42": [
    "n02086079",
    "Pekinese, Pekingese, Peke"
  ],
  "43": [
    "n02484975",
    "guenon, guenon monkey"
  ],
  "44": [
    "n02137549",
    "mongoose"
  ],
  "45": [
    "n02500267",
    "indri, indris, Indri indri, Indri brevicaudatus"
  ],
  "46": [
    "n02129604",
    "tiger, Panthera tigris"
  ],
  "47": [
    "n02396427",
    "wild boar, boar, Sus scrofa"
  ],
  "48": [
    "n02391049",
    "zebra"
  ],
  "49": [
    "n02412080",
    "ram, tup"
  ],
  "50": [
    "n02480495",
    "orangutan, orang, orangutang, Pongo pygmaeus"
  ],
  "51": [
    "n02110806",
    "basenji"
  ],
  "52": [
    "n02128385",
    "leopard, Panthera pardus"
  ],
  "53": [
    "n02100583",
    "vizsla, Hungarian pointer"
  ],
  "54": [
    "n02494079",
    "squirrel monkey, Saimiri sciureus"
  ],
  "55": [
    "n02123597",
    "Siamese cat, Siamese"
  ],
  "56": [
    "n02481823",
    "chimpanzee, chimp, Pan troglodytes"
  ],
  "57": [
    "n02105505",
    "komondor"
  ],
  "58": [
    "n02489166",
    "proboscis monkey, Nasalis larvatus"
  ],
  "59": [
    "n02364673",
    "guinea pig, Cavia cobaya"
  ],
  "60": [
    "n02114548",
    "white wolf, Arctic wolf, Canis lupus tundrarum"
  ],
  "61": [
    "n02134084",
    "ice bear, polar bear, Ursus Maritimus, Thalarctos maritimus"
  ],
  "62": [
    "n02480855",
    "gorilla, Gorilla gorilla"
  ],
  "63": [
    "n02403003",
    "ox"
  ],
  "64": [
    "n02108551",
    "Tibetan mastiff"
  ],
  "65": [
    "n02493793",
    "spider monkey, Ateles geoffroyi"
  ],
  "66": [
    "n02107142",
    "Doberman, Doberman pinscher"
  ],
  "67": [
    "n02397096",
    "warthog"
  ],
  "68": [
    "n02437312",
    "Arabian camel, dromedary, Camelus dromedarius"
  ],
  "69": [
    "n02483708",
    "siamang, Hylobates syndactylus, Symphalangus syndactylus"
  ],
  "70": [
    "n02099601",
    "golden retriever"
  ],
  "71": [
    "n02106166",
    "Border collie"
  ],
  "72": [
    "n02326432",
    "hare"
  ],
  "73": [
    "n02108089",
    "boxer"
  ],
  "74": [
    "n02486261",
    "patas, hussar monkey, Erythrocebus patas"
  ],
  "75": [
    "n02486410",
    "baboon"
  ],
  "76": [
    "n02487347",
    "macaque"
  ],
  "77": [
    "n02492035",
    "capuchin, ringtail, Cebus capucinus"
  ],
  "78": [
    "n02099267",
    "flat-coated retriever"
  ],
  "79": [
    "n02395406",
    "hog, pig, grunter, squealer, Sus scrofa"
  ],
  "80": [
    "n02109961",
    "Eskimo dog, husky"
  ],
  "81": [
    "n02101388",
    "Brittany spaniel"
  ],
  "82": [
    "n03187595",
    "dial telephone, dial phone"
  ],
  "83": [
    "n03733281",
    "maze, labyrinth"
  ],
  "84": [
    "n02101006",
    "Gordon setter"
  ],
  "85": [
    "n02115641",
    "dingo, warrigal, warragal, Canis dingo"
  ],
  "86": [
    "n02342885",
    "hamster"
  ],
  "87": [
    "n02120079",
    "Arctic fox, white fox, Alopex lagopus"
  ],
  "88": [
    "n02408429",
    "water buffalo, water ox, Asiatic buffalo, Bubalus bubalis"
  ],
  "89": [
    "n02133161",
    "American black bear, black bear, Ursus americanus, Euarctos americanus"
  ],
  "90": [
    "n02328150",
    "Angora, Angora rabbit"
  ],
  "91": [
    "n02410509",
    "bison"
  ],
  "92": [
    "n02492660",
    "howler monkey, howler"
  ],
  "93": [
    "n02398521",
    "hippopotamus, hippo, river horse, Hippopotamus amphibius"
  ],
  "94": [
    "n02510455",
    "giant panda, panda, panda bear, coon bear, Ailuropoda melanoleuca"
  ],
  "95": [
    "n02123045",
    "tabby, tabby cat"
  ],
  "96": [
    "n02490219",
    "marmoset"
  ],
  "97": [
    "n02109525",
    "Saint Bernard, St Bernard"
  ],
  "98": [
    "n02454379",
    "armadillo"
  ],
  "99": [
    "n02090379",
    "redbone"
  ],
  "100": [
    "n02443114",
    "polecat, fitch, foulmart, foumart, Mustela putorius"
  ],
  "101": [
    "n02361337",
    "marmot"
  ],
  "102": [
    "n02483362",
    "gibbon, Hylobates lar"
  ],
  "103": [
    "n02437616",
    "llama"
  ],
  "104": [
    "n02325366",
    "wood rabbit, cottontail, cottontail rabbit"
  ],
  "105": [
    "n02129165",
    "lion, king of beasts, Panthera leo"
  ],
  "106": [
    "n02100877",
    "Irish setter, red setter"
  ],
  "107": [
    "n02074367",
    "dugong, Dugong dugon"
  ],
  "108": [
    "n02504013",
    "Indian elephant, Elephas maximus"
  ],
  "109": [
    "n02363005",
    "beaver"
  ],
  "110": [
    "n02497673",
    "Madagascar cat, ring-tailed lemur, Lemur catta"
  ],
  "111": [
    "n02087394",
    "Rhodesian ridgeback"
  ],
  "112": [
    "n02127052",
    "lynx, catamount"
  ],
  "113": [
    "n02116738",
    "African hunting dog, hyena dog, Cape hunting dog, Lycaon pictus"
  ],
  "114": [
    "n02488291",
    "langur"
  ],
  "115": [
    "n02114367",
    "timber wolf, grey wolf, gray wolf, Canis lupus"
  ],
  "116": [
    "n02130308",
    "cheetah, chetah, Acinonyx jubatus"
  ],
  "117": [
    "n02134418",
    "sloth bear, Melursus ursinus, Ursus ursinus"
  ],
  "118": [
    "n02106662",
    "German shepherd, German shepherd dog, German police dog, alsatian"
  ],
  "119": [
    "n02444819",
    "otter"
  ],
  "120": [
    "n01882714",
    "koala, koala bear, kangaroo bear, native bear, Phascolarctos cinereus"
  ],
  "121": [
    "n01871265",
    "tusker"
  ],
  "122": [
    "n01872401",
    "echidna, spiny anteater, anteater"
  ],
  "123": [
    "n01877812",
    "wallaby, brush kangaroo"
  ],
  "124": [
    "n01873310",
    "platypus, duckbill, duckbilled platypus, duck-billed platypus, Ornithorhynchus anatinus"
  ],
  "125": [
    "n01883070",
    "wombat"
  ],
  "126": [
    "n04086273",
    "revolver, six-gun, six-shooter"
  ],
  "127": [
    "n04507155",
    "umbrella"
  ],
  "128": [
    "n04147183",
    "schooner"
  ],
  "129": [
    "n04254680",
    "soccer ball"
  ],
  "130": [
    "n02672831",
    "accordion, piano accordion, squeeze box"
  ],
  "131": [
    "n02219486",
    "ant, emmet, pismire"
  ],
  "132": [
    "n02317335",
    "starfish, sea star"
  ],
  "133": [
    "n01968897",
    "chambered nautilus, pearly nautilus, nautilus"
  ],
  "134": [
    "n03452741",
    "grand piano, grand"
  ],
  "135": [
    "n03642806",
    "laptop, laptop computer"
  ],
  "136": [
    "n07745940",
    "strawberry"
  ],
  "137": [
    "n02690373",
    "airliner"
  ],
  "138": [
    "n04552348",
    "warplane, military plane"
  ],
  "139": [
    "n02692877",
    "airship, dirigible"
  ],
  "140": [
    "n02782093",
    "balloon"
  ],
  "141": [
    "n04266014",
    "space shuttle"
  ],
  "142": [
    "n03344393",
    "fireboat"
  ],
  "143": [
    "n03447447",
    "gondola"
  ],
  "144": [
    "n04273569",
    "speedboat"
  ],
  "145": [
    "n03662601",
    "lifeboat"
  ],
  "146": [
    "n02951358",
    "canoe"
  ],
  "147": [
    "n04612504",
    "yawl"
  ],
  "148": [
    "n02981792",
    "catamaran"
  ],
  "149": [
    "n04483307",
    "trimaran"
  ],
  "150": [
    "n03095699",
    "container ship, containership, container vessel"
  ],
  "151": [
    "n03673027",
    "liner, ocean liner"
  ],
  "152": [
    "n03947888",
    "pirate, pirate ship"
  ],
  "153": [
    "n02687172",
    "aircraft carrier, carrier, flattop, attack aircraft carrier"
  ],
  "154": [
    "n04347754",
    "submarine, pigboat, sub, U-boat"
  ],
  "155": [
    "n04606251",
    "wreck"
  ],
  "156": [
    "n03478589",
    "half track"
  ],
  "157": [
    "n04389033",
    "tank, army tank, armored combat vehicle, armoured combat vehicle"
  ],
  "158": [
    "n03773504",
    "missile"
  ],
  "159": [
    "n02860847",
    "bobsled, bobsleigh, bob"
  ],
  "160": [
    "n03218198",
    "dogsled, dog sled, dog sleigh"
  ],
  "161": [
    "n02835271",
    "bicycle-built-for-two, tandem bicycle, tandem"
  ],
  "162": [
    "n03792782",
    "mountain bike, all-terrain bike, off-roader"
  ],
  "163": [
    "n03393912",
    "freight car"
  ],
  "164": [
    "n03895866",
    "passenger car, coach, carriage"
  ],
  "165": [
    "n02797295",
    "barrow, garden cart, lawn cart, wheelbarrow"
  ],
  "166": [
    "n04204347",
    "shopping cart"
  ],
  "167": [
    "n03791053",
    "motor scooter, scooter"
  ],
  "168": [
    "n03384352",
    "forklift"
  ],
  "169": [
    "n03272562",
    "electric locomotive"
  ],
  "170": [
    "n04310018",
    "steam locomotive"
  ],
  "171": [
    "n02704792",
    "amphibian, amphibious vehicle"
  ],
  "172": [
    "n02701002",
    "ambulance"
  ],
  "173": [
    "n02814533",
    "beach wagon, station wagon, wagon, estate car, beach waggon, station waggon, waggon"
  ],
  "174": [
    "n02930766",
    "cab, hack, taxi, taxicab"
  ],
  "175": [
    "n03100240",
    "convertible"
  ],
  "176": [
    "n03594945",
    "jeep, landrover"
  ],
  "177": [
    "n03670208",
    "limousine, limo"
  ],
  "178": [
    "n03770679",
    "minivan"
  ],
  "179": [
    "n03777568",
    "Model T"
  ],
  "180": [
    "n04037443",
    "racer, race car, racing car"
  ],
  "181": [
    "n04285008",
    "sports car, sport car"
  ],
  "182": [
    "n03444034",
    "go-kart"
  ],
  "183": [
    "n03445924",
    "golfcart, golf cart"
  ],
  "184": [
    "n03785016",
    "moped"
  ],
  "185": [
    "n04252225",
    "snowplow, snowplough"
  ],
  "186": [
    "n03345487",
    "fire engine, fire truck"
  ],
  "187": [
    "n03417042",
    "garbage truck, dustcart"
  ],
  "188": [
    "n03930630",
    "pickup, pickup truck"
  ],
  "189": [
    "n04461696",
    "tow truck, tow car, wrecker"
  ],
  "190": [
    "n04467665",
    "trailer truck, tractor trailer, trucking rig, rig, articulated lorry, semi"
  ],
  "191": [
    "n03796401",
    "moving van"
  ],
  "192": [
    "n03977966",
    "police van, police wagon, paddy wagon, patrol wagon, wagon, black Maria"
  ],
  "193": [
    "n04065272",
    "recreational vehicle, RV, R.V."
  ],
  "194": [
    "n04335435",
    "streetcar, tram, tramcar, trolley, trolley car"
  ],
  "195": [
    "n04252077",
    "snowmobile"
  ],
  "196": [
    "n04465501",
    "tractor"
  ],
  "197": [
    "n03776460",
    "mobile home, manufactured home"
  ],
  "198": [
    "n04482393",
    "tricycle, trike, velocipede"
  ],
  "199": [
    "n04509417",
    "unicycle, monocycle"
  ],
  "200": [
    "n03538406",
    "horse cart, horse-cart"
  ],
  "201": [
    "n03788365",
    "mosquito net"
  ],
  "202": [
    "n03868242",
    "oxcart"
  ],
  "203": [
    "n02804414",
    "bassinet"
  ],
  "204": [
    "n03125729",
    "cradle"
  ],
  "205": [
    "n03131574",
    "crib, cot"
  ],
  "206": [
    "n03388549",
    "four-poster"
  ],
  "207": [
    "n02870880",
    "bookcase"
  ],
  "208": [
    "n03018349",
    "china cabinet, china closet"
  ],
  "209": [
    "n03742115",
    "medicine chest, medicine cabinet"
  ],
  "210": [
    "n03016953",
    "chiffonier, commode"
  ],
  "211": [
    "n04380533",
    "table lamp"
  ],
  "212": [
    "n03337140",
    "file, file cabinet, filing cabinet"
  ],
  "213": [
    "n03902125",
    "pay-phone, pay-station"
  ],
  "214": [
    "n03891251",
    "park bench"
  ],
  "215": [
    "n02791124",
    "barber chair"
  ],
  "216": [
    "n04429376",
    "throne"
  ],
  "217": [
    "n03376595",
    "folding chair"
  ],
  "218": [
    "n04099969",
    "rocking chair, rocker"
  ],
  "219": [
    "n04344873",
    "studio couch, day bed"
  ],
  "220": [
    "n04447861",
    "toilet seat"
  ],
  "221": [
    "n03179701",
    "desk"
  ],
  "222": [
    "n03982430",
    "pool table, billiard table, snooker table"
  ],
  "223": [
    "n03201208",
    "dining table, board"
  ],
  "224": [
    "n03290653",
    "entertainment center"
  ],
  "225": [
    "n04550184",
    "wardrobe, closet, press"
  ],
  "226": [
    "n07742313",
    "Granny Smith"
  ],
  "227": [
    "n07747607",
    "orange"
  ],
  "228": [
    "n07749582",
    "lemon"
  ],
  "229": [
    "n07753113",
    "fig"
  ],
  "230": [
    "n07753275",
    "pineapple, ananas"
  ],
  "231": [
    "n07753592",
    "banana"
  ],
  "232": [
    "n07754684",
    "jackfruit, jak, jack"
  ],
  "233": [
    "n07760859",
    "custard apple"
  ],
  "234": [
    "n07768694",
    "pomegranate"
  ],
  "235": [
    "n12267677",
    "acorn"
  ],
  "236": [
    "n12620546",
    "hip, rose hip, rosehip"
  ],
  "237": [
    "n13133613",
    "ear, spike, capitulum"
  ],
  "238": [
    "n11879895",
    "rapeseed"
  ],
  "239": [
    "n12144580",
    "corn"
  ],
  "240": [
    "n12768682",
    "buckeye, horse chestnut, conker"
  ],
  "241": [
    "n03854065",
    "organ, pipe organ"
  ],
  "242": [
    "n04515003",
    "upright, upright piano"
  ],
  "243": [
    "n03017168",
    "chime, bell, gong"
  ],
  "244": [
    "n03249569",
    "drum, membranophone, tympan"
  ],
  "245": [
    "n03447721",
    "gong, tam-tam"
  ],
  "246": [
    "n03720891",
    "maraca"
  ],
  "247": [
    "n03721384",
    "marimba, xylophone"
  ],
  "248": [
    "n04311174",
    "steel drum"
  ],
  "249": [
    "n02787622",
    "banjo"
  ],
  "250": [
    "n02992211",
    "cello, violoncello"
  ],
  "251": [
    "n03637318",
    "lampshade, lamp shade"
  ],
  "252": [
    "n03495258",
    "harp"
  ],
  "253": [
    "n02676566",
    "acoustic guitar"
  ],
  "254": [
    "n03272010",
    "electric guitar"
  ],
  "255": [
    "n03110669",
    "cornet, horn, trumpet, trump"
  ],
  "256": [
    "n03394916",
    "French horn, horn"
  ],
  "257": [
    "n04487394",
    "trombone"
  ],
  "258": [
    "n03494278",
    "harmonica, mouth organ, harp, mouth harp"
  ],
  "259": [
    "n03840681",
    "ocarina, sweet potato"
  ],
  "260": [
    "n03884397",
    "panpipe, pandean pipe, syrinx"
  ],
  "261": [
    "n02804610",
    "bassoon"
  ],
  "262": [
    "n04141076",
    "sax, saxophone"
  ],
  "263": [
    "n03372029",
    "flute, transverse flute"
  ],
  "264": [
    "n11939491",
    "daisy"
  ],
  "265": [
    "n12057211",
    "yellow lady's slipper, yellow lady-slipper, Cypripedium calceolus, Cypripedium parviflorum"
  ],
  "266": [
    "n09246464",
    "cliff, drop, drop-off"
  ],
  "267": [
    "n09468604",
    "valley, vale"
  ],
  "268": [
    "n09193705",
    "alp"
  ],
  "269": [
    "n09472597",
    "volcano"
  ],
  "270": [
    "n09399592",
    "promontory, headland, head, foreland"
  ],
  "271": [
    "n09421951",
    "sandbar, sand bar"
  ],
  "272": [
    "n09256479",
    "coral reef"
  ],
  "273": [
    "n09332890",
    "lakeside, lakeshore"
  ],
  "274": [
    "n09428293",
    "seashore, coast, seacoast, sea-coast"
  ],
  "275": [
    "n09288635",
    "geyser"
  ],
  "276": [
    "n03498962",
    "hatchet"
  ],
  "277": [
    "n03041632",
    "cleaver, meat cleaver, chopper"
  ],
  "278": [
    "n03658185",
    "letter opener, paper knife, paperknife"
  ],
  "279": [
    "n03954731",
    "plane, carpenter's plane, woodworking plane"
  ],
  "280": [
    "n03995372",
    "power drill"
  ],
  "281": [
    "n03649909",
    "lawn mower, mower"
  ],
  "282": [
    "n03481172",
    "hammer"
  ],
  "283": [
    "n03109150",
    "corkscrew, bottle screw"
  ],
  "284": [
    "n02951585",
    "can opener, tin opener"
  ],
  "285": [
    "n03970156",
    "plunger, plumber's helper"
  ],
  "286": [
    "n04154565",
    "screwdriver"
  ],
  "287": [
    "n04208210",
    "shovel"
  ],
  "288": [
    "n03967562",
    "plow, plough"
  ],
  "289": [
    "n03000684",
    "chain saw, chainsaw"
  ],
  "290": [
    "n01514668",
    "cock"
  ],
  "291": [
    "n01514859",
    "hen"
  ],
  "292": [
    "n01518878",
    "ostrich, Struthio camelus"
  ],
  "293": [
    "n01530575",
    "brambling, Fringilla montifringilla"
  ],
  "294": [
    "n01531178",
    "goldfinch, Carduelis carduelis"
  ],
  "295": [
    "n01532829",
    "house finch, linnet, Carpodacus mexicanus"
  ],
  "296": [
    "n01534433",
    "junco, snowbird"
  ],
  "297": [
    "n01537544",
    "indigo bunting, indigo finch, indigo bird, Passerina cyanea"
  ],
  "298": [
    "n01558993",
    "robin, American robin, Turdus migratorius"
  ],
  "299": [
    "n01560419",
    "bulbul"
  ],
  "300": [
    "n01580077",
    "jay"
  ],
  "301": [
    "n01582220",
    "magpie"
  ],
  "302": [
    "n01592084",
    "chickadee"
  ],
  "303": [
    "n01601694",
    "water ouzel, dipper"
  ],
  "304": [
    "n01608432",
    "kite"
  ],
  "305": [
    "n01614925",
    "bald eagle, American eagle, Haliaeetus leucocephalus"
  ],
  "306": [
    "n01616318",
    "vulture"
  ],
  "307": [
    "n01622779",
    "great grey owl, great gray owl, Strix nebulosa"
  ],
  "308": [
    "n01795545",
    "black grouse"
  ],
  "309": [
    "n01796340",
    "ptarmigan"
  ],
  "310": [
    "n01797886",
    "ruffed grouse, partridge, Bonasa umbellus"
  ],
  "311": [
    "n01798484",
    "prairie chicken, prairie grouse, prairie fowl"
  ],
  "312": [
    "n01806143",
    "peacock"
  ],
  "313": [
    "n01806567",
    "quail"
  ],
  "314": [
    "n01807496",
    "partridge"
  ],
  "315": [
    "n01817953",
    "African grey, African gray, Psittacus erithacus"
  ],
  "316": [
    "n01818515",
    "macaw"
  ],
  "317": [
    "n01819313",
    "sulphur-crested cockatoo, Kakatoe galerita, Cacatua galerita"
  ],
  "318": [
    "n01820546",
    "lorikeet"
  ],
  "319": [
    "n01824575",
    "coucal"
  ],
  "320": [
    "n01828970",
    "bee eater"
  ],
  "321": [
    "n01829413",
    "hornbill"
  ],
  "322": [
    "n01833805",
    "hummingbird"
  ],
  "323": [
    "n01843065",
    "jacamar"
  ],
  "324": [
    "n01843383",
    "toucan"
  ],
  "325": [
    "n01847000",
    "drake"
  ],
  "326": [
    "n01855032",
    "red-breasted merganser, Mergus serrator"
  ],
  "327": [
    "n01855672",
    "goose"
  ],
  "328": [
    "n01860187",
    "black swan, Cygnus atratus"
  ],
  "329": [
    "n02002556",
    "white stork, Ciconia ciconia"
  ],
  "330": [
    "n02002724",
    "black stork, Ciconia nigra"
  ],
  "331": [
    "n02006656",
    "spoonbill"
  ],
  "332": [
    "n02007558",
    "flamingo"
  ],
  "333": [
    "n02009912",
    "American egret, great white heron, Egretta albus"
  ],
  "334": [
    "n02009229",
    "little blue heron, Egretta caerulea"
  ],
  "335": [
    "n02011460",
    "bittern"
  ],
  "336": [
    "n02012849",
    "crane"
  ],
  "337": [
    "n02013706",
    "limpkin, Aramus pictus"
  ],
  "338": [
    "n02018207",
    "American coot, marsh hen, mud hen, water hen, Fulica americana"
  ],
  "339": [
    "n02018795",
    "bustard"
  ],
  "340": [
    "n02025239",
    "ruddy turnstone, Arenaria interpres"
  ],
  "341": [
    "n02027492",
    "red-backed sandpiper, dunlin, Erolia alpina"
  ],
  "342": [
    "n02028035",
    "redshank, Tringa totanus"
  ],
  "343": [
    "n02033041",
    "dowitcher"
  ],
  "344": [
    "n02037110",
    "oystercatcher, oyster catcher"
  ],
  "345": [
    "n02017213",
    "European gallinule, Porphyrio porphyrio"
  ],
  "346": [
    "n02051845",
    "pelican"
  ],
  "347": [
    "n02056570",
    "king penguin, Aptenodytes patagonica"
  ],
  "348": [
    "n02058221",
    "albatross, mollymawk"
  ],
  "349": [
    "n01484850",
    "great white shark, white shark, man-eater, man-eating shark, Carcharodon carcharias"
  ],
  "350": [
    "n01491361",
    "tiger shark, Galeocerdo cuvieri"
  ],
  "351": [
    "n01494475",
    "hammerhead, hammerhead shark"
  ],
  "352": [
    "n01496331",
    "electric ray, crampfish, numbfish, torpedo"
  ],
  "353": [
    "n01498041",
    "stingray"
  ],
  "354": [
    "n02514041",
    "barracouta, snoek"
  ],
  "355": [
    "n02536864",
    "coho, cohoe, coho salmon, blue jack, silver salmon, Oncorhynchus kisutch"
  ],
  "356": [
    "n01440764",
    "tench, Tinca tinca"
  ],
  "357": [
    "n01443537",
    "goldfish, Carassius auratus"
  ],
  "358": [
    "n02526121",
    "eel"
  ],
  "359": [
    "n02606052",
    "rock beauty, Holocanthus tricolor"
  ],
  "360": [
    "n02607072",
    "anemone fish"
  ],
  "361": [
    "n02643566",
    "lionfish"
  ],
  "362": [
    "n02655020",
    "puffer, pufferfish, blowfish, globefish"
  ],
  "363": [
    "n02640242",
    "sturgeon"
  ],
  "364": [
    "n02641379",
    "gar, garfish, garpike, billfish, Lepisosteus osseus"
  ],
  "365": [
    "n01664065",
    "loggerhead, loggerhead turtle, Caretta caretta"
  ],
  "366": [
    "n01667114",
    "mud turtle"
  ],
  "367": [
    "n01667778",
    "terrapin"
  ],
  "368": [
    "n01669191",
    "box turtle, box tortoise"
  ],
  "369": [
    "n01675722",
    "banded gecko"
  ],
  "370": [
    "n01677366",
    "common iguana, iguana, Iguana iguana"
  ],
  "371": [
    "n01682714",
    "American chameleon, anole, Anolis carolinensis"
  ],
  "372": [
    "n01685808",
    "whiptail, whiptail lizard"
  ],
  "373": [
    "n01687978",
    "agama"
  ],
  "374": [
    "n01688243",
    "frilled lizard, Chlamydosaurus kingi"
  ],
  "375": [
    "n01689811",
    "alligator lizard"
  ],
  "376": [
    "n01692333",
    "Gila monster, Heloderma suspectum"
  ],
  "377": [
    "n01693334",
    "green lizard, Lacerta viridis"
  ],
  "378": [
    "n01694178",
    "African chameleon, Chamaeleo chamaeleon"
  ],
  "379": [
    "n01695060",
    "Komodo dragon, Komodo lizard, dragon lizard, giant lizard, Varanus komodoensis"
  ],
  "380": [
    "n01704323",
    "triceratops"
  ],
  "381": [
    "n01697457",
    "African crocodile, Nile crocodile, Crocodylus niloticus"
  ],
  "382": [
    "n01698640",
    "American alligator, Alligator mississipiensis"
  ],
  "383": [
    "n01728572",
    "thunder snake, worm snake, Carphophis amoenus"
  ],
  "384": [
    "n01728920",
    "ringneck snake, ring-necked snake, ring snake"
  ],
  "385": [
    "n01729322",
    "hognose snake, puff adder, sand viper"
  ],
  "386": [
    "n01729977",
    "green snake, grass snake"
  ],
  "387": [
    "n01734418",
    "king snake, kingsnake"
  ],
  "388": [
    "n01735189",
    "garter snake, grass snake"
  ],
  "389": [
    "n01737021",
    "water snake"
  ],
  "390": [
    "n01739381",
    "vine snake"
  ],
  "391": [
    "n01740131",
    "night snake, Hypsiglena torquata"
  ],
  "392": [
    "n01742172",
    "boa constrictor, Constrictor constrictor"
  ],
  "393": [
    "n01744401",
    "rock python, rock snake, Python sebae"
  ],
  "394": [
    "n01748264",
    "Indian cobra, Naja naja"
  ],
  "395": [
    "n01749939",
    "green mamba"
  ],
  "396": [
    "n01751748",
    "sea snake"
  ],
  "397": [
    "n01753488",
    "horned viper, cerastes, sand viper, horned asp, Cerastes cornutus"
  ],
  "398": [
    "n04326547",
    "stone wall"
  ],
  "399": [
    "n01756291",
    "sidewinder, horned rattlesnake, Crotalus cerastes"
  ],
  "400": [
    "n01629819",
    "European fire salamander, Salamandra salamandra"
  ],
  "401": [
    "n01630670",
    "common newt, Triturus vulgaris"
  ],
  "402": [
    "n01631663",
    "eft"
  ],
  "403": [
    "n01632458",
    "spotted salamander, Ambystoma maculatum"
  ],
  "404": [
    "n01632777",
    "axolotl, mud puppy, Ambystoma mexicanum"
  ],
  "405": [
    "n01641577",
    "bullfrog, Rana catesbeiana"
  ],
  "406": [
    "n01644373",
    "tree frog, tree-frog"
  ],
  "407": [
    "n01644900",
    "tailed frog, bell toad, ribbed toad, tailed toad, Ascaphus trui"
  ],
  "408": [
    "n04579432",
    "whistle"
  ],
  "409": [
    "n04592741",
    "wing"
  ],
  "410": [
    "n03876231",
    "paintbrush"
  ],
  "411": [
    "n03868863",
    "oxygen mask"
  ],
  "412": [
    "n04251144",
    "snorkel"
  ],
  "413": [
    "n03691459",
    "loudspeaker, speaker, speaker unit, loudspeaker system, speaker system"
  ],
  "414": [
    "n03759954",
    "microphone, mike"
  ],
  "415": [
    "n04152593",
    "screen, CRT screen"
  ],
  "416": [
    "n03793489",
    "mouse, computer mouse"
  ],
  "417": [
    "n03271574",
    "electric fan, blower"
  ],
  "418": [
    "n03843555",
    "oil filter"
  ],
  "419": [
    "n04332243",
    "strainer"
  ],
  "420": [
    "n04265275",
    "space heater"
  ],
  "421": [
    "n04330267",
    "stove"
  ],
  "422": [
    "n03467068",
    "guillotine"
  ],
  "423": [
    "n02794156",
    "barometer"
  ],
  "424": [
    "n04118776",
    "rule, ruler"
  ],
  "425": [
    "n03841143",
    "odometer, hodometer, mileometer, milometer"
  ],
  "426": [
    "n04141975",
    "scale, weighing machine"
  ],
  "427": [
    "n02708093",
    "analog clock"
  ],
  "428": [
    "n03196217",
    "digital clock"
  ],
  "429": [
    "n04548280",
    "wall clock"
  ],
  "430": [
    "n03544143",
    "hourglass"
  ],
  "431": [
    "n04355338",
    "sundial"
  ],
  "432": [
    "n03891332",
    "parking meter"
  ],
  "433": [
    "n04328186",
    "stopwatch, stop watch"
  ],
  "434": [
    "n03197337",
    "digital watch"
  ],
  "435": [
    "n04317175",
    "stethoscope"
  ],
  "436": [
    "n04376876",
    "syringe"
  ],
  "437": [
    "n03706229",
    "magnetic compass"
  ],
  "438": [
    "n02841315",
    "binoculars, field glasses, opera glasses"
  ],
  "439": [
    "n04009552",
    "projector"
  ],
  "440": [
    "n04356056",
    "sunglasses, dark glasses, shades"
  ],
  "441": [
    "n03692522",
    "loupe, jeweler's loupe"
  ],
  "442": [
    "n04044716",
    "radio telescope, radio reflector"
  ],
  "443": [
    "n02879718",
    "bow"
  ],
  "444": [
    "n02950826",
    "cannon"
  ],
  "445": [
    "n02749479",
    "assault rifle, assault gun"
  ],
  "446": [
    "n04090263",
    "rifle"
  ],
  "447": [
    "n04008634",
    "projectile, missile"
  ],
  "448": [
    "n03085013",
    "computer keyboard, keypad"
  ],
  "449": [
    "n04505470",
    "typewriter keyboard"
  ],
  "450": [
    "n03126707",
    "crane"
  ],
  "451": [
    "n03666591",
    "lighter, light, igniter, ignitor"
  ],
  "452": [
    "n02666196",
    "abacus"
  ],
  "453": [
    "n02977058",
    "cash machine, cash dispenser, automated teller machine, automatic teller machine, automated teller, automatic teller, ATM"
  ],
  "454": [
    "n04238763",
    "slide rule, slipstick"
  ],
  "455": [
    "n03180011",
    "desktop computer"
  ],
  "456": [
    "n03485407",
    "hand-held computer, hand-held microcomputer"
  ],
  "457": [
    "n03832673",
    "notebook, notebook computer"
  ],
  "458": [
    "n03874599",
    "padlock"
  ],
  "459": [
    "n03496892",
    "harvester, reaper"
  ],
  "460": [
    "n04428191",
    "thresher, thrasher, threshing machine"
  ],
  "461": [
    "n04004767",
    "printer"
  ],
  "462": [
    "n04243546",
    "slot, one-armed bandit"
  ],
  "463": [
    "n04525305",
    "vending machine"
  ],
  "464": [
    "n04179913",
    "sewing machine"
  ],
  "465": [
    "n03602883",
    "joystick"
  ],
  "466": [
    "n04372370",
    "switch, electric switch, electrical switch"
  ],
  "467": [
    "n03532672",
    "hook, claw"
  ],
  "468": [
    "n02974003",
    "car wheel"
  ],
  "469": [
    "n03874293",
    "paddlewheel, paddle wheel"
  ],
  "470": [
    "n03944341",
    "pinwheel"
  ],
  "471": [
    "n03992509",
    "potter's wheel"
  ],
  "472": [
    "n03425413",
    "gas pump, gasoline pump, petrol pump, island dispenser"
  ],
  "473": [
    "n02966193",
    "carousel, carrousel, merry-go-round, roundabout, whirligig"
  ],
  "474": [
    "n04371774",
    "swing"
  ],
  "475": [
    "n04067472",
    "reel"
  ],
  "476": [
    "n04040759",
    "radiator"
  ],
  "477": [
    "n04019541",
    "puck, hockey puck"
  ],
  "478": [
    "n03492542",
    "hard disc, hard disk, fixed disk"
  ],
  "479": [
    "n04355933",
    "sunglass"
  ],
  "480": [
    "n03929660",
    "pick, plectrum, plectron"
  ],
  "481": [
    "n02965783",
    "car mirror"
  ],
  "482": [
    "n04258138",
    "solar dish, solar collector, solar furnace"
  ],
  "483": [
    "n04074963",
    "remote control, remote"
  ],
  "484": [
    "n03208938",
    "disk brake, disc brake"
  ],
  "485": [
    "n02910353",
    "buckle"
  ],
  "486": [
    "n03476684",
    "hair slide"
  ],
  "487": [
    "n03627232",
    "knot"
  ],
  "488": [
    "n03075370",
    "combination lock"
  ],
  "489": [
    "n06359193",
    "web site, website, internet site, site"
  ],
  "490": [
    "n03804744",
    "nail"
  ],
  "491": [
    "n04127249",
    "safety pin"
  ],
  "492": [
    "n04153751",
    "screw"
  ],
  "493": [
    "n03803284",
    "muzzle"
  ],
  "494": [
    "n04162706",
    "seat belt, seatbelt"
  ],
  "495": [
    "n04228054",
    "ski"
  ],
  "496": [
    "n02948072",
    "candle, taper, wax light"
  ],
  "497": [
    "n03590841",
    "jack-o'-lantern"
  ],
  "498": [
    "n04286575",
    "spotlight, spot"
  ],
  "499": [
    "n04456115",
    "torch"
  ],
  "500": [
    "n03814639",
    "neck brace"
  ],
  "501": [
    "n03933933",
    "pier"
  ],
  "502": [
    "n04485082",
    "tripod"
  ],
  "503": [
    "n03733131",
    "maypole"
  ],
  "504": [
    "n03483316",
    "hand blower, blow dryer, blow drier, hair dryer, hair drier"
  ],
  "505": [
    "n03794056",
    "mousetrap"
  ],
  "506": [
    "n04275548",
    "spider web, spider's web"
  ],
  "507": [
    "n01768244",
    "trilobite"
  ],
  "508": [
    "n01770081",
    "harvestman, daddy longlegs, Phalangium opilio"
  ],
  "509": [
    "n01770393",
    "scorpion"
  ],
  "510": [
    "n01773157",
    "black and gold garden spider, Argiope aurantia"
  ],
  "511": [
    "n01773549",
    "barn spider, Araneus cavaticus"
  ],
  "512": [
    "n01773797",
    "garden spider, Aranea diademata"
  ],
  "513": [
    "n01774384",
    "black widow, Latrodectus mactans"
  ],
  "514": [
    "n01774750",
    "tarantula"
  ],
  "515": [
    "n01775062",
    "wolf spider, hunting spider"
  ],
  "516": [
    "n01776313",
    "tick"
  ],
  "517": [
    "n01784675",
    "centipede"
  ],
  "518": [
    "n01990800",
    "isopod"
  ],
  "519": [
    "n01978287",
    "Dungeness crab, Cancer magister"
  ],
  "520": [
    "n01978455",
    "rock crab, Cancer irroratus"
  ],
  "521": [
    "n01980166",
    "fiddler crab"
  ],
  "522": [
    "n01981276",
    "king crab, Alaska crab, Alaskan king crab, Alaska king crab, Paralithodes camtschatica"
  ],
  "523": [
    "n01983481",
    "American lobster, Northern lobster, Maine lobster, Homarus americanus"
  ],
  "524": [
    "n01984695",
    "spiny lobster, langouste, rock lobster, crawfish, crayfish, sea crawfish"
  ],
  "525": [
    "n01985128",
    "crayfish, crawfish, crawdad, crawdaddy"
  ],
  "526": [
    "n01986214",
    "hermit crab"
  ],
  "527": [
    "n02165105",
    "tiger beetle"
  ],
  "528": [
    "n02165456",
    "ladybug, ladybeetle, lady beetle, ladybird, ladybird beetle"
  ],
  "529": [
    "n02167151",
    "ground beetle, carabid beetle"
  ],
  "530": [
    "n02168699",
    "long-horned beetle, longicorn, longicorn beetle"
  ],
  "531": [
    "n02169497",
    "leaf beetle, chrysomelid"
  ],
  "532": [
    "n02172182",
    "dung beetle"
  ],
  "533": [
    "n02174001",
    "rhinoceros beetle"
  ],
  "534": [
    "n02177972",
    "weevil"
  ],
  "535": [
    "n02190166",
    "fly"
  ],
  "536": [
    "n02206856",
    "bee"
  ],
  "537": [
    "n02226429",
    "grasshopper, hopper"
  ],
  "538": [
    "n02229544",
    "cricket"
  ],
  "539": [
    "n02231487",
    "walking stick, walkingstick, stick insect"
  ],
  "540": [
    "n02233338",
    "cockroach, roach"
  ],
  "541": [
    "n02236044",
    "mantis, mantid"
  ],
  "542": [
    "n02256656",
    "cicada, cicala"
  ],
  "543": [
    "n02259212",
    "leafhopper"
  ],
  "544": [
    "n02264363",
    "lacewing, lacewing fly"
  ],
  "545": [
    "n02268443",
    "dragonfly, darning needle, devil's darning needle, sewing needle, snake feeder, snake doctor, mosquito hawk, skeeter hawk"
  ],
  "546": [
    "n02268853",
    "damselfly"
  ],
  "547": [
    "n02276258",
    "admiral"
  ],
  "548": [
    "n02277742",
    "ringlet, ringlet butterfly"
  ],
  "549": [
    "n02279972",
    "monarch, monarch butterfly, milkweed butterfly, Danaus plexippus"
  ],
  "550": [
    "n02280649",
    "cabbage butterfly"
  ],
  "551": [
    "n02281406",
    "sulphur butterfly, sulfur butterfly"
  ],
  "552": [
    "n02281787",
    "lycaenid, lycaenid butterfly"
  ],
  "553": [
    "n01910747",
    "jellyfish"
  ],
  "554": [
    "n01914609",
    "sea anemone, anemone"
  ],
  "555": [
    "n01917289",
    "brain coral"
  ],
  "556": [
    "n01924916",
    "flatworm, platyhelminth"
  ],
  "557": [
    "n01930112",
    "nematode, nematode worm, roundworm"
  ],
  "558": [
    "n01943899",
    "conch"
  ],
  "559": [
    "n01944390",
    "snail"
  ],
  "560": [
    "n01945685",
    "slug"
  ],
  "561": [
    "n01950731",
    "sea slug, nudibranch"
  ],
  "562": [
    "n01955084",
    "chiton, coat-of-mail shell, sea cradle, polyplacophore"
  ],
  "563": [
    "n02319095",
    "sea urchin"
  ],
  "564": [
    "n02321529",
    "sea cucumber, holothurian"
  ],
  "565": [
    "n03584829",
    "iron, smoothing iron"
  ],
  "566": [
    "n03297495",
    "espresso maker"
  ],
  "567": [
    "n03761084",
    "microwave, microwave oven"
  ],
  "568": [
    "n03259280",
    "Dutch oven"
  ],
  "569": [
    "n04111531",
    "rotisserie"
  ],
  "570": [
    "n04442312",
    "toaster"
  ],
  "571": [
    "n04542943",
    "waffle iron"
  ],
  "572": [
    "n04517823",
    "vacuum, vacuum cleaner"
  ],
  "573": [
    "n03207941",
    "dishwasher, dish washer, dishwashing machine"
  ],
  "574": [
    "n04070727",
    "refrigerator, icebox"
  ],
  "575": [
    "n04554684",
    "washer, automatic washer, washing machine"
  ],
  "576": [
    "n03133878",
    "Crock Pot"
  ],
  "577": [
    "n03400231",
    "frying pan, frypan, skillet"
  ],
  "578": [
    "n04596742",
    "wok"
  ],
  "579": [
    "n02939185",
    "caldron, cauldron"
  ],
  "580": [
    "n03063689",
    "coffeepot"
  ],
  "581": [
    "n04398044",
    "teapot"
  ],
  "582": [
    "n04270147",
    "spatula"
  ],
  "583": [
    "n02699494",
    "altar"
  ],
  "584": [
    "n04486054",
    "triumphal arch"
  ],
  "585": [
    "n03899768",
    "patio, terrace"
  ],
  "586": [
    "n04311004",
    "steel arch bridge"
  ],
  "587": [
    "n04366367",
    "suspension bridge"
  ],
  "588": [
    "n04532670",
    "viaduct"
  ],
  "589": [
    "n02793495",
    "barn"
  ],
  "590": [
    "n03457902",
    "greenhouse, nursery, glasshouse"
  ],
  "591": [
    "n03877845",
    "palace"
  ],
  "592": [
    "n03781244",
    "monastery"
  ],
  "593": [
    "n03661043",
    "library"
  ],
  "594": [
    "n02727426",
    "apiary, bee house"
  ],
  "595": [
    "n02859443",
    "boathouse"
  ],
  "596": [
    "n03028079",
    "church, church building"
  ],
  "597": [
    "n03788195",
    "mosque"
  ],
  "598": [
    "n04346328",
    "stupa, tope"
  ],
  "599": [
    "n03956157",
    "planetarium"
  ],
  "600": [
    "n04081281",
    "restaurant, eating house, eating place, eatery"
  ],
  "601": [
    "n03032252",
    "cinema, movie theater, movie theatre, movie house, picture palace"
  ],
  "602": [
    "n03529860",
    "home theater, home theatre"
  ],
  "603": [
    "n03697007",
    "lumbermill, sawmill"
  ],
  "604": [
    "n03065424",
    "coil, spiral, volute, whorl, helix"
  ],
  "605": [
    "n03837869",
    "obelisk"
  ],
  "606": [
    "n04458633",
    "totem pole"
  ],
  "607": [
    "n02980441",
    "castle"
  ],
  "608": [
    "n04005630",
    "prison, prison house"
  ],
  "609": [
    "n03461385",
    "grocery store, grocery, food market, market"
  ],
  "610": [
    "n02776631",
    "bakery, bakeshop, bakehouse"
  ],
  "611": [
    "n02791270",
    "barbershop"
  ],
  "612": [
    "n02871525",
    "bookshop, bookstore, bookstall"
  ],
  "613": [
    "n02927161",
    "butcher shop, meat market"
  ],
  "614": [
    "n03089624",
    "confectionery, confectionary, candy store"
  ],
  "615": [
    "n04200800",
    "shoe shop, shoe-shop, shoe store"
  ],
  "616": [
    "n04443257",
    "tobacco shop, tobacconist shop, tobacconist"
  ],
  "617": [
    "n04462240",
    "toyshop"
  ],
  "618": [
    "n03388043",
    "fountain"
  ],
  "619": [
    "n03042490",
    "cliff dwelling"
  ],
  "620": [
    "n04613696",
    "yurt"
  ],
  "621": [
    "n03216828",
    "dock, dockage, docking facility"
  ],
  "622": [
    "n02892201",
    "brass, memorial tablet, plaque"
  ],
  "623": [
    "n03743016",
    "megalith, megalithic structure"
  ],
  "624": [
    "n02788148",
    "bannister, banister, balustrade, balusters, handrail"
  ],
  "625": [
    "n02894605",
    "breakwater, groin, groyne, mole, bulwark, seawall, jetty"
  ],
  "626": [
    "n03160309",
    "dam, dike, dyke"
  ],
  "627": [
    "n03000134",
    "chainlink fence"
  ],
  "628": [
    "n03930313",
    "picket fence, paling"
  ],
  "629": [
    "n04604644",
    "worm fence, snake fence, snake-rail fence, Virginia fence"
  ],
  "630": [
    "n01755581",
    "diamondback, diamondback rattlesnake, Crotalus adamanteus"
  ],
  "631": [
    "n03459775",
    "grille, radiator grille"
  ],
  "632": [
    "n04239074",
    "sliding door"
  ],
  "633": [
    "n04501370",
    "turnstile"
  ],
  "634": [
    "n03792972",
    "mountain tent"
  ],
  "635": [
    "n04149813",
    "scoreboard"
  ],
  "636": [
    "n03530642",
    "honeycomb"
  ],
  "637": [
    "n03961711",
    "plate rack"
  ],
  "638": [
    "n03903868",
    "pedestal, plinth, footstall"
  ],
  "639": [
    "n02814860",
    "beacon, lighthouse, beacon light, pharos"
  ],
  "640": [
    "n01665541",
    "leatherback turtle, leatherback, leathery turtle, Dermochelys coriacea"
  ],
  "641": [
    "n07711569",
    "mashed potato"
  ],
  "642": [
    "n07720875",
    "bell pepper"
  ],
  "643": [
    "n07714571",
    "head cabbage"
  ],
  "644": [
    "n07714990",
    "broccoli"
  ],
  "645": [
    "n07715103",
    "cauliflower"
  ],
  "646": [
    "n07716358",
    "zucchini, courgette"
  ],
  "647": [
    "n07716906",
    "spaghetti squash"
  ],
  "648": [
    "n07717410",
    "acorn squash"
  ],
  "649": [
    "n07717556",
    "butternut squash"
  ],
  "650": [
    "n07718472",
    "cucumber, cuke"
  ],
  "651": [
    "n07718747",
    "artichoke, globe artichoke"
  ],
  "652": [
    "n07730033",
    "cardoon"
  ],
  "653": [
    "n07734744",
    "mushroom"
  ],
  "654": [
    "n04209239",
    "shower curtain"
  ],
  "655": [
    "n03594734",
    "jean, blue jean, denim"
  ],
  "656": [
    "n02971356",
    "carton"
  ],
  "657": [
    "n03485794",
    "handkerchief, hankie, hanky, hankey"
  ],
  "658": [
    "n04133789",
    "sandal"
  ],
  "659": [
    "n02747177",
    "ashcan, trash can, garbage can, wastebin, ash bin, ash-bin, ashbin, dustbin, trash barrel, trash bin"
  ],
  "660": [
    "n04125021",
    "safe"
  ],
  "661": [
    "n07579787",
    "plate"
  ],
  "662": [
    "n03814906",
    "necklace"
  ],
  "663": [
    "n03134739",
    "croquet ball"
  ],
  "664": [
    "n03404251",
    "fur coat"
  ],
  "665": [
    "n04423845",
    "thimble"
  ],
  "666": [
    "n03877472",
    "pajama, pyjama, pj's, jammies"
  ],
  "667": [
    "n04120489",
    "running shoe"
  ],
  "668": [
    "n03838899",
    "oboe, hautboy, hautbois"
  ],
  "669": [
    "n03062245",
    "cocktail shaker"
  ],
  "670": [
    "n03014705",
    "chest"
  ],
  "671": [
    "n03717622",
    "manhole cover"
  ],
  "672": [
    "n03777754",
    "modem"
  ],
  "673": [
    "n04493381",
    "tub, vat"
  ],
  "674": [
    "n04476259",
    "tray"
  ],
  "675": [
    "n02777292",
    "balance beam, beam"
  ],
  "676": [
    "n07693725",
    "bagel, beigel"
  ],
  "677": [
    "n04536866",
    "violin, fiddle"
  ],
  "678": [
    "n03998194",
    "prayer rug, prayer mat"
  ],
  "679": [
    "n03617480",
    "kimono"
  ],
  "680": [
    "n07590611",
    "hot pot, hotpot"
  ],
  "681": [
    "n04579145",
    "whiskey jug"
  ],
  "682": [
    "n03623198",
    "knee pad"
  ],
  "683": [
    "n07248320",
    "book jacket, dust cover, dust jacket, dust wrapper"
  ],
  "684": [
    "n04277352",
    "spindle"
  ],
  "685": [
    "n04229816",
    "ski mask"
  ],
  "686": [
    "n02823428",
    "beer bottle"
  ],
  "687": [
    "n03127747",
    "crash helmet"
  ],
  "688": [
    "n02877765",
    "bottlecap"
  ],
  "689": [
    "n04435653",
    "tile roof"
  ],
  "690": [
    "n03724870",
    "mask"
  ],
  "691": [
    "n03710637",
    "maillot"
  ],
  "692": [
    "n03920288",
    "Petri dish"
  ],
  "693": [
    "n03379051",
    "football helmet"
  ],
  "694": [
    "n02807133",
    "bathing cap, swimming cap"
  ],
  "695": [
    "n04399382",
    "teddy, teddy bear"
  ],
  "696": [
    "n03527444",
    "holster"
  ],
  "697": [
    "n03983396",
    "pop bottle, soda bottle"
  ],
  "698": [
    "n03924679",
    "photocopier"
  ],
  "699": [
    "n04532106",
    "vestment"
  ],
  "700": [
    "n06785654",
    "crossword puzzle, crossword"
  ],
  "701": [
    "n03445777",
    "golf ball"
  ],
  "702": [
    "n07613480",
    "trifle"
  ],
  "703": [
    "n04350905",
    "suit, suit of clothes"
  ],
  "704": [
    "n04562935",
    "water tower"
  ],
  "705": [
    "n03325584",
    "feather boa, boa"
  ],
  "706": [
    "n03045698",
    "cloak"
  ],
  "707": [
    "n07892512",
    "red wine"
  ],
  "708": [
    "n03250847",
    "drumstick"
  ],
  "709": [
    "n04192698",
    "shield, buckler"
  ],
  "710": [
    "n03026506",
    "Christmas stocking"
  ],
  "711": [
    "n03534580",
    "hoopskirt, crinoline"
  ],
  "712": [
    "n07565083",
    "menu"
  ],
  "713": [
    "n04296562",
    "stage"
  ],
  "714": [
    "n02869837",
    "bonnet, poke bonnet"
  ],
  "715": [
    "n07871810",
    "meat loaf, meatloaf"
  ],
  "716": [
    "n02799071",
    "baseball"
  ],
  "717": [
    "n03314780",
    "face powder"
  ],
  "718": [
    "n04141327",
    "scabbard"
  ],
  "719": [
    "n04357314",
    "sunscreen, sunblock, sun blocker"
  ],
  "720": [
    "n02823750",
    "beer glass"
  ],
  "721": [
    "n13052670",
    "hen-of-the-woods, hen of the woods, Polyporus frondosus, Grifola frondosa"
  ],
  "722": [
    "n07583066",
    "guacamole"
  ],
  "723": [
    "n04599235",
    "wool, woolen, woollen"
  ],
  "724": [
    "n07802026",
    "hay"
  ],
  "725": [
    "n02883205",
    "bow tie, bow-tie, bowtie"
  ],
  "726": [
    "n03709823",
    "mailbag, postbag"
  ],
  "727": [
    "n04560804",
    "water jug"
  ],
  "728": [
    "n02909870",
    "bucket, pail"
  ],
  "729": [
    "n03207743",
    "dishrag, dishcloth"
  ],
  "730": [
    "n04263257",
    "soup bowl"
  ],
  "731": [
    "n07932039",
    "eggnog"
  ],
  "732": [
    "n03786901",
    "mortar"
  ],
  "733": [
    "n04479046",
    "trench coat"
  ],
  "734": [
    "n03873416",
    "paddle, boat paddle"
  ],
  "735": [
    "n02999410",
    "chain"
  ],
  "736": [
    "n04367480",
    "swab, swob, mop"
  ],
  "737": [
    "n03775546",
    "mixing bowl"
  ],
  "738": [
    "n07875152",
    "potpie"
  ],
  "739": [
    "n04591713",
    "wine bottle"
  ],
  "740": [
    "n04201297",
    "shoji"
  ],
  "741": [
    "n02916936",
    "bulletproof vest"
  ],
  "742": [
    "n03240683",
    "drilling platform, offshore rig"
  ],
  "743": [
    "n02840245",
    "binder, ring-binder"
  ],
  "744": [
    "n02963159",
    "cardigan"
  ],
  "745": [
    "n04370456",
    "sweatshirt"
  ],
  "746": [
    "n03991062",
    "pot, flowerpot"
  ],
  "747": [
    "n02843684",
    "birdhouse"
  ],
  "748": [
    "n03599486",
    "jinrikisha, ricksha, rickshaw"
  ],
  "749": [
    "n03482405",
    "hamper"
  ],
  "750": [
    "n03942813",
    "ping-pong ball"
  ],
  "751": [
    "n03908618",
    "pencil box, pencil case"
  ],
  "752": [
    "n07584110",
    "consomme"
  ],
  "753": [
    "n02730930",
    "apron"
  ],
  "754": [
    "n04023962",
    "punching bag, punch bag, punching ball, punchball"
  ],
  "755": [
    "n02769748",
    "backpack, back pack, knapsack, packsack, rucksack, haversack"
  ],
  "756": [
    "n10148035",
    "groom, bridegroom"
  ],
  "757": [
    "n02817516",
    "bearskin, busby, shako"
  ],
  "758": [
    "n03908714",
    "pencil sharpener"
  ],
  "759": [
    "n02906734",
    "broom"
  ],
  "760": [
    "n02667093",
    "abaya"
  ],
  "761": [
    "n03787032",
    "mortarboard"
  ],
  "762": [
    "n03980874",
    "poncho"
  ],
  "763": [
    "n03141823",
    "crutch"
  ],
  "764": [
    "n03976467",
    "Polaroid camera, Polaroid Land camera"
  ],
  "765": [
    "n04264628",
    "space bar"
  ],
  "766": [
    "n07930864",
    "cup"
  ],
  "767": [
    "n04039381",
    "racket, racquet"
  ],
  "768": [
    "n06874185",
    "traffic light, traffic signal, stoplight"
  ],
  "769": [
    "n04033901",
    "quill, quill pen"
  ],
  "770": [
    "n04041544",
    "radio, wireless"
  ],
  "771": [
    "n02128757",
    "snow leopard, ounce, Panthera uncia"
  ],
  "772": [
    "n07860988",
    "dough"
  ],
  "773": [
    "n03146219",
    "cuirass"
  ],
  "774": [
    "n03763968",
    "military uniform"
  ],
  "775": [
    "n03676483",
    "lipstick, lip rouge"
  ],
  "776": [
    "n04209133",
    "shower cap"
  ],
  "777": [
    "n03782006",
    "monitor"
  ],
  "778": [
    "n03857828",
    "oscilloscope, scope, cathode-ray oscilloscope, CRO"
  ],
  "779": [
    "n03775071",
    "mitten"
  ],
  "780": [
    "n02892767",
    "brassiere, bra, bandeau"
  ],
  "781": [
    "n07684084",
    "French loaf"
  ],
  "782": [
    "n04522168",
    "vase"
  ],
  "783": [
    "n03764736",
    "milk can"
  ],
  "784": [
    "n04118538",
    "rugby ball"
  ],
  "785": [
    "n03887697",
    "paper towel"
  ],
  "786": [
    "n13044778",
    "earthstar"
  ],
  "787": [
    "n03291819",
    "envelope"
  ],
  "788": [
    "n03770439",
    "miniskirt, mini"
  ],
  "789": [
    "n03124170",
    "cowboy hat, ten-gallon hat"
  ],
  "790": [
    "n04487081",
    "trolleybus, trolley coach, trackless trolley"
  ],
  "791": [
    "n03916031",
    "perfume, essence"
  ],
  "792": [
    "n02808440",
    "bathtub, bathing tub, bath, tub"
  ],
  "793": [
    "n07697537",
    "hotdog, hot dog, red hot"
  ],
  "794": [
    "n12985857",
    "coral fungus"
  ],
  "795": [
    "n02917067",
    "bullet train, bullet"
  ],
  "796": [
    "n03938244",
    "pillow"
  ],
  "797": [
    "n15075141",
    "toilet tissue, toilet paper, bathroom tissue"
  ],
  "798": [
    "n02978881",
    "cassette"
  ],
  "799": [
    "n02966687",
    "carpenter's kit, tool kit"
  ],
  "800": [
    "n03633091",
    "ladle"
  ],
  "801": [
    "n13040303",
    "stinkhorn, carrion fungus"
  ],
  "802": [
    "n03690938",
    "lotion"
  ],
  "803": [
    "n03476991",
    "hair spray"
  ],
  "804": [
    "n02669723",
    "academic gown, academic robe, judge's robe"
  ],
  "805": [
    "n03220513",
    "dome"
  ],
  "806": [
    "n03127925",
    "crate"
  ],
  "807": [
    "n04584207",
    "wig"
  ],
  "808": [
    "n07880968",
    "burrito"
  ],
  "809": [
    "n03937543",
    "pill bottle"
  ],
  "810": [
    "n03000247",
    "chain mail, ring mail, mail, chain armor, chain armour, ring armor, ring armour"
  ],
  "811": [
    "n04418357",
    "theater curtain, theatre curtain"
  ],
  "812": [
    "n04590129",
    "window shade"
  ],
  "813": [
    "n02795169",
    "barrel, cask"
  ],
  "814": [
    "n04553703",
    "washbasin, handbasin, washbowl, lavabo, wash-hand basin"
  ],
  "815": [
    "n02783161",
    "ballpoint, ballpoint pen, ballpen, Biro"
  ],
  "816": [
    "n02802426",
    "basketball"
  ],
  "817": [
    "n02808304",
    "bath towel"
  ],
  "818": [
    "n03124043",
    "cowboy boot"
  ],
  "819": [
    "n03450230",
    "gown"
  ],
  "820": [
    "n04589890",
    "window screen"
  ],
  "821": [
    "n12998815",
    "agaric"
  ],
  "822": [
    "n02113799",
    "standard poodle"
  ],
  "823": [
    "n02992529",
    "cellular telephone, cellular phone, cellphone, cell, mobile phone"
  ],
  "824": [
    "n03825788",
    "nipple"
  ],
  "825": [
    "n02790996",
    "barbell"
  ],
  "826": [
    "n03710193",
    "mailbox, letter box"
  ],
  "827": [
    "n03630383",
    "lab coat, laboratory coat"
  ],
  "828": [
    "n03347037",
    "fire screen, fireguard"
  ],
  "829": [
    "n03769881",
    "minibus"
  ],
  "830": [
    "n03871628",
    "packet"
  ],
  "831": [
    "n02132136",
    "brown bear, bruin, Ursus arctos"
  ],
  "832": [
    "n03976657",
    "pole"
  ],
  "833": [
    "n03535780",
    "horizontal bar, high bar"
  ],
  "834": [
    "n04259630",
    "sombrero"
  ],
  "835": [
    "n03929855",
    "pickelhaube"
  ],
  "836": [
    "n04049303",
    "rain barrel"
  ],
  "837": [
    "n04548362",
    "wallet, billfold, notecase, pocketbook"
  ],
  "838": [
    "n02979186",
    "cassette player"
  ],
  "839": [
    "n06596364",
    "comic book"
  ],
  "840": [
    "n03935335",
    "piggy bank, penny bank"
  ],
  "841": [
    "n06794110",
    "street sign"
  ],
  "842": [
    "n02825657",
    "bell cote, bell cot"
  ],
  "843": [
    "n03388183",
    "fountain pen"
  ],
  "844": [
    "n04591157",
    "Windsor tie"
  ],
  "845": [
    "n04540053",
    "volleyball"
  ],
  "846": [
    "n03866082",
    "overskirt"
  ],
  "847": [
    "n04136333",
    "sarong"
  ],
  "848": [
    "n04026417",
    "purse"
  ],
  "849": [
    "n02865351",
    "bolo tie, bolo, bola tie, bola"
  ],
  "850": [
    "n02834397",
    "bib"
  ],
  "851": [
    "n03888257",
    "parachute, chute"
  ],
  "852": [
    "n04235860",
    "sleeping bag"
  ],
  "853": [
    "n04404412",
    "television, television system"
  ],
  "854": [
    "n04371430",
    "swimming trunks, bathing trunks"
  ],
  "855": [
    "n03733805",
    "measuring cup"
  ],
  "856": [
    "n07920052",
    "espresso"
  ],
  "857": [
    "n07873807",
    "pizza, pizza pie"
  ],
  "858": [
    "n02895154",
    "breastplate, aegis, egis"
  ],
  "859": [
    "n04204238",
    "shopping basket"
  ],
  "860": [
    "n04597913",
    "wooden spoon"
  ],
  "861": [
    "n04131690",
    "saltshaker, salt shaker"
  ],
  "862": [
    "n07836838",
    "chocolate sauce, chocolate syrup"
  ],
  "863": [
    "n09835506",
    "ballplayer, baseball player"
  ],
  "864": [
    "n03443371",
    "goblet"
  ],
  "865": [
    "n13037406",
    "gyromitra"
  ],
  "866": [
    "n04336792",
    "stretcher"
  ],
  "867": [
    "n04557648",
    "water bottle"
  ],
  "868": [
    "n02445715",
    "skunk, polecat, wood pussy"
  ],
  "869": [
    "n04254120",
    "soap dispenser"
  ],
  "870": [
    "n03595614",
    "jersey, T-shirt, tee shirt"
  ],
  "871": [
    "n04146614",
    "school bus"
  ],
  "872": [
    "n03598930",
    "jigsaw puzzle"
  ],
  "873": [
    "n03958227",
    "plastic bag"
  ],
  "874": [
    "n04069434",
    "reflex camera"
  ],
  "875": [
    "n03188531",
    "diaper, nappy, napkin"
  ],
  "876": [
    "n02786058",
    "Band Aid"
  ],
  "877": [
    "n07615774",
    "ice lolly, lolly, lollipop, popsicle"
  ],
  "878": [
    "n04525038",
    "velvet"
  ],
  "879": [
    "n04409515",
    "tennis ball"
  ],
  "880": [
    "n03424325",
    "gasmask, respirator, gas helmet"
  ],
  "881": [
    "n03223299",
    "doormat, welcome mat"
  ],
  "882": [
    "n03680355",
    "Loafer"
  ],
  "883": [
    "n07614500",
    "ice cream, icecream"
  ],
  "884": [
    "n07695742",
    "pretzel"
  ],
  "885": [
    "n04033995",
    "quilt, comforter, comfort, puff"
  ],
  "886": [
    "n03710721",
    "maillot, tank suit"
  ],
  "887": [
    "n04392985",
    "tape player"
  ],
  "888": [
    "n03047690",
    "clog, geta, patten, sabot"
  ],
  "889": [
    "n03584254",
    "iPod"
  ],
  "890": [
    "n13054560",
    "bolete"
  ],
  "891": [
    "n02138441",
    "meerkat, mierkat"
  ],
  "892": [
    "n10565667",
    "scuba diver"
  ],
  "893": [
    "n03950228",
    "pitcher, ewer"
  ],
  "894": [
    "n03729826",
    "matchstick"
  ],
  "895": [
    "n02837789",
    "bikini, two-piece"
  ],
  "896": [
    "n04254777",
    "sock"
  ],
  "897": [
    "n02988304",
    "CD player"
  ],
  "898": [
    "n03657121",
    "lens cap, lens cover"
  ],
  "899": [
    "n04417672",
    "thatch, thatched roof"
  ],
  "900": [
    "n04523525",
    "vault"
  ],
  "901": [
    "n02815834",
    "beaker"
  ],
  "902": [
    "n09229709",
    "bubble"
  ],
  "903": [
    "n07697313",
    "cheeseburger"
  ],
  "904": [
    "n03888605",
    "parallel bars, bars"
  ],
  "905": [
    "n03355925",
    "flagpole, flagstaff"
  ],
  "906": [
    "n03063599",
    "coffee mug"
  ],
  "907": [
    "n04116512",
    "rubber eraser, rubber, pencil eraser"
  ],
  "908": [
    "n04325704",
    "stole"
  ],
  "909": [
    "n07831146",
    "carbonara"
  ],
  "910": [
    "n03255030",
    "dumbbell"
  ],
  "911": [
    "href=\"ht",
    ""
  ],
  "912": [
    "n02102040",
    "English springer, English springer spaniel"
  ],
  "913": [
    "n02110063",
    "malamute, malemute, Alaskan malamute"
  ],
  "914": [
    "n02089867",
    "Walker hound, Walker foxhound"
  ],
  "915": [
    "n02102177",
    "Welsh springer spaniel"
  ],
  "916": [
    "n02091134",
    "whippet"
  ],
  "917": [
    "n02092339",
    "Weimaraner"
  ],
  "918": [
    "n02098105",
    "soft-coated wheaten terrier"
  ],
  "919": [
    "n02096437",
    "Dandie Dinmont, Dandie Dinmont terrier"
  ],
  "920": [
    "n02105641",
    "Old English sheepdog, bobtail"
  ],
  "921": [
    "n02091635",
    "otterhound, otter hound"
  ],
  "922": [
    "n02088466",
    "bloodhound, sleuthhound"
  ],
  "923": [
    "n02096051",
    "Airedale, Airedale terrier"
  ],
  "924": [
    "n02097130",
    "giant schnauzer"
  ],
  "925": [
    "n02089078",
    "black-and-tan coonhound"
  ],
  "926": [
    "n02086910",
    "papillon"
  ],
  "927": [
    "n02113978",
    "Mexican hairless"
  ],
  "928": [
    "n02113186",
    "Cardigan, Cardigan Welsh corgi"
  ],
  "929": [
    "n02105162",
    "malinois"
  ],
  "930": [
    "n02098413",
    "Lhasa, Lhasa apso"
  ],
  "931": [
    "n02091467",
    "Norwegian elkhound, elkhound"
  ],
  "932": [
    "n02106550",
    "Rottweiler"
  ],
  "933": [
    "n02091831",
    "Saluki, gazelle hound"
  ],
  "934": [
    "n02104365",
    "schipperke"
  ],
  "935": [
    "n02112706",
    "Brabancon griffon"
  ],
  "936": [
    "n02098286",
    "West Highland white terrier"
  ],
  "937": [
    "n02095889",
    "Sealyham terrier, Sealyham"
  ],
  "938": [
    "n02090721",
    "Irish wolfhound"
  ],
  "939": [
    "n02108000",
    "EntleBucher"
  ],
  "940": [
    "n02108915",
    "French bulldog"
  ],
  "941": [
    "n02107683",
    "Bernese mountain dog"
  ],
  "942": [
    "n02085936",
    "Maltese dog, Maltese terrier, Maltese"
  ],
  "943": [
    "n02094114",
    "Norfolk terrier"
  ],
  "944": [
    "n02087046",
    "toy terrier"
  ],
  "945": [
    "n02096177",
    "cairn, cairn terrier"
  ],
  "946": [
    "n02105056",
    "groenendael"
  ],
  "947": [
    "n02101556",
    "clumber, clumber spaniel"
  ],
  "948": [
    "n02088094",
    "Afghan hound, Afghan"
  ],
  "949": [
    "n02085782",
    "Japanese spaniel"
  ],
  "950": [
    "n02090622",
    "borzoi, Russian wolfhound"
  ],
  "951": [
    "n02113624",
    "toy poodle"
  ],
  "952": [
    "n02093859",
    "Kerry blue terrier"
  ],
  "953": [
    "n02097298",
    "Scotch terrier, Scottish terrier, Scottie"
  ],
  "954": [
    "n02096585",
    "Boston bull, Boston terrier"
  ],
  "955": [
    "n02107574",
    "Greater Swiss Mountain dog"
  ],
  "956": [
    "n02107908",
    "Appenzeller"
  ],
  "957": [
    "n02086240",
    "Shih-Tzu"
  ],
  "958": [
    "n02102973",
    "Irish water spaniel"
  ],
  "959": [
    "n02112018",
    "Pomeranian"
  ],
  "960": [
    "n02093647",
    "Bedlington terrier"
  ],
  "961": [
    "n02097047",
    "miniature schnauzer"
  ],
  "962": [
    "n02106030",
    "collie"
  ],
  "963": [
    "n02093991",
    "Irish terrier"
  ],
  "964": [
    "n02110627",
    "affenpinscher, monkey pinscher, monkey dog"
  ],
  "965": [
    "n02097658",
    "silky terrier, Sydney silky"
  ],
  "966": [
    "n02088364",
    "beagle"
  ],
  "967": [
    "n02111129",
    "Leonberg"
  ],
  "968": [
    "n02100236",
    "German short-haired pointer"
  ],
  "969": [
    "n02115913",
    "dhole, Cuon alpinus"
  ],
  "970": [
    "n02099849",
    "Chesapeake Bay retriever"
  ],
  "971": [
    "n02108422",
    "bull mastiff"
  ],
  "972": [
    "n02104029",
    "kuvasz"
  ],
  "973": [
    "n02110958",
    "pug, pug-dog"
  ],
  "974": [
    "n02099429",
    "curly-coated retriever"
  ],
  "975": [
    "n02094258",
    "Norwich terrier"
  ],
  "976": [
    "n02112350",
    "keeshond"
  ],
  "977": [
    "n02095570",
    "Lakeland terrier"
  ],
  "978": [
    "n02097209",
    "standard schnauzer"
  ],
  "979": [
    "n02097474",
    "Tibetan terrier, chrysanthemum dog"
  ],
  "980": [
    "n02095314",
    "wire-haired fox terrier"
  ],
  "981": [
    "n02088238",
    "basset, basset hound"
  ],
  "982": [
    "n02112137",
    "chow, chow chow"
  ],
  "983": [
    "n02093428",
    "American Staffordshire terrier, Staffordshire terrier, American pit bull terrier, pit bull terrier"
  ],
  "984": [
    "n02105855",
    "Shetland sheepdog, Shetland sheep dog, Shetland"
  ],
  "985": [
    "n02111500",
    "Great Pyrenees"
  ],
  "986": [
    "n02085620",
    "Chihuahua"
  ],
  "987": [
    "n02099712",
    "Labrador retriever"
  ],
  "988": [
    "n02111889",
    "Samoyed, Samoyede"
  ],
  "989": [
    "n02088632",
    "bluetick"
  ],
  "990": [
    "n02105412",
    "kelpie"
  ],
  "991": [
    "n02107312",
    "miniature pinscher"
  ],
  "992": [
    "n02091032",
    "Italian greyhound"
  ],
  "993": [
    "n02102318",
    "cocker spaniel, English cocker spaniel, cocker"
  ],
  "994": [
    "n02102480",
    "Sussex spaniel"
  ],
  "995": [
    "n02113023",
    "Pembroke, Pembroke Welsh corgi"
  ],
  "996": [
    "n02086646",
    "Blenheim spaniel"
  ],
  "997": [
    "n02091244",
    "Ibizan hound, Ibizan Podenco"
  ],
  "998": [
    "n02089973",
    "English foxhound"
  ],
  "999": [
    "n02105251",
    "briard"
  ],
  "1000": [
    "n02093754",
    "Border terrier"
  ]
}